<annotation>
    <folder>keras-retinanet</folder>
    <filename>HazeDr_Google_75.png</filename>
    <path>/ssd2/yeyuan/dehaze/docker/keras-retinanet/HazeDr_Google_75.png</path>
    <source>
        <database>Unknown</database>
    </source>
    <size>
        <width>0</width>
        <height>0</height>
        <depth>3</depth>
    </size>
    <segmented>0</segmented>
    <object>
        <name>car</name>
        <pose>Unspecified</pose>
        <truncated>0</truncated>
        <difficult>0.9239539</difficult>
        <bndbox>
            <xmin>419.6599</xmin>
            <ymin>154.45119</ymin>
            <xmax>481.16248</xmax>
            <ymax>216.76509</ymax>
        </bndbox>
    </object>    <object>
        <name>motorcycle</name>
        <pose>Unspecified</pose>
        <truncated>0</truncated>
        <difficult>0.8135754</difficult>
        <bndbox>
            <xmin>4.4411645</xmin>
            <ymin>151.99394</ymin>
            <xmax>66.07063</xmax>
            <ymax>251.75163</ymax>
        </bndbox>
    </object>    <object>
        <name>person</name>
        <pose>Unspecified</pose>
        <truncated>0</truncated>
        <difficult>0.8097223</difficult>
        <bndbox>
            <xmin>287.6743</xmin>
            <ymin>133.51518</ymin>
            <xmax>356.46805</xmax>
            <ymax>205.66278</ymax>
        </bndbox>
    </object>    <object>
        <name>person</name>
        <pose>Unspecified</pose>
        <truncated>0</truncated>
        <difficult>0.8093033</difficult>
        <bndbox>
            <xmin>10.501194</xmin>
            <ymin>110.788734</ymin>
            <xmax>70.63361</xmax>
            <ymax>217.89032</ymax>
        </bndbox>
    </object>    <object>
        <name>motorcycle</name>
        <pose>Unspecified</pose>
        <truncated>0</truncated>
        <difficult>0.8091872</difficult>
        <bndbox>
            <xmin>284.1691</xmin>
            <ymin>169.1349</ymin>
            <xmax>373.31845</xmax>
            <ymax>311.10617</ymax>
        </bndbox>
    </object>    <object>
        <name>car</name>
        <pose>Unspecified</pose>
        <truncated>0</truncated>
        <difficult>0.68510103</difficult>
        <bndbox>
            <xmin>338.12967</xmin>
            <ymin>155.3822</ymin>
            <xmax>383.24228</xmax>
            <ymax>208.48288</ymax>
        </bndbox>
    </object>    <object>
        <name>bus</name>
        <pose>Unspecified</pose>
        <truncated>0</truncated>
        <difficult>0.5868061</difficult>
        <bndbox>
            <xmin>143.38264</xmin>
            <ymin>117.13054</ymin>
            <xmax>277.35886</xmax>
            <ymax>264.61966</ymax>
        </bndbox>
    </object>    <object>
        <name>car</name>
        <pose>Unspecified</pose>
        <truncated>0</truncated>
        <difficult>0.54857904</difficult>
        <bndbox>
            <xmin>298.05566</xmin>
            <ymin>152.05313</ymin>
            <xmax>380.8063</xmax>
            <ymax>209.18987</ymax>
        </bndbox>
    </object>    <object>
        <name>car</name>
        <pose>Unspecified</pose>
        <truncated>0</truncated>
        <difficult>0.5457113</difficult>
        <bndbox>
            <xmin>377.39664</xmin>
            <ymin>162.14497</ymin>
            <xmax>419.8018</xmax>
            <ymax>196.52237</ymax>
        </bndbox>
    </object>    <object>
        <name>person</name>
        <pose>Unspecified</pose>
        <truncated>0</truncated>
        <difficult>0.5096544</difficult>
        <bndbox>
            <xmin>46.322403</xmin>
            <ymin>114.63866</ymin>
            <xmax>69.31074</xmax>
            <ymax>166.74657</ymax>
        </bndbox>
    </object>    <object>
        <name>person</name>
        <pose>Unspecified</pose>
        <truncated>0</truncated>
        <difficult>0.4854415</difficult>
        <bndbox>
            <xmin>294.08826</xmin>
            <ymin>139.18102</ymin>
            <xmax>375.11383</xmax>
            <ymax>241.64482</ymax>
        </bndbox>
    </object>    <object>
        <name>truck</name>
        <pose>Unspecified</pose>
        <truncated>0</truncated>
        <difficult>0.48032108</difficult>
        <bndbox>
            <xmin>145.38521</xmin>
            <ymin>118.077065</ymin>
            <xmax>276.60455</xmax>
            <ymax>263.1747</ymax>
        </bndbox>
    </object>    <object>
        <name>motorcycle</name>
        <pose>Unspecified</pose>
        <truncated>0</truncated>
        <difficult>0.4662628</difficult>
        <bndbox>
            <xmin>280.1237</xmin>
            <ymin>146.97205</ymin>
            <xmax>377.6115</xmax>
            <ymax>208.64174</ymax>
        </bndbox>
    </object>    <object>
        <name>person</name>
        <pose>Unspecified</pose>
        <truncated>0</truncated>
        <difficult>0.46039265</difficult>
        <bndbox>
            <xmin>47.38321</xmin>
            <ymin>115.95992</ymin>
            <xmax>71.147675</xmax>
            <ymax>214.16615</ymax>
        </bndbox>
    </object>    <object>
        <name>car</name>
        <pose>Unspecified</pose>
        <truncated>0</truncated>
        <difficult>0.39171585</difficult>
        <bndbox>
            <xmin>349.17377</xmin>
            <ymin>159.66559</ymin>
            <xmax>406.44272</xmax>
            <ymax>204.56833</ymax>
        </bndbox>
    </object>    <object>
        <name>person</name>
        <pose>Unspecified</pose>
        <truncated>0</truncated>
        <difficult>0.36538464</difficult>
        <bndbox>
            <xmin>23.451967</xmin>
            <ymin>111.426704</ymin>
            <xmax>67.86811</xmax>
            <ymax>161.76483</ymax>
        </bndbox>
    </object>    <object>
        <name>motorcycle</name>
        <pose>Unspecified</pose>
        <truncated>0</truncated>
        <difficult>0.3590365</difficult>
        <bndbox>
            <xmin>8.547666</xmin>
            <ymin>114.27727</ymin>
            <xmax>69.08992</xmax>
            <ymax>223.32423</ymax>
        </bndbox>
    </object>    <object>
        <name>person</name>
        <pose>Unspecified</pose>
        <truncated>0</truncated>
        <difficult>0.35653287</difficult>
        <bndbox>
            <xmin>287.4441</xmin>
            <ymin>166.76572</ymin>
            <xmax>371.94943</xmax>
            <ymax>307.57208</ymax>
        </bndbox>
    </object>    <object>
        <name>person</name>
        <pose>Unspecified</pose>
        <truncated>0</truncated>
        <difficult>0.34962192</difficult>
        <bndbox>
            <xmin>6.0119667</xmin>
            <ymin>148.91574</ymin>
            <xmax>67.78472</xmax>
            <ymax>242.1858</ymax>
        </bndbox>
    </object>    <object>
        <name>car</name>
        <pose>Unspecified</pose>
        <truncated>0</truncated>
        <difficult>0.33119294</difficult>
        <bndbox>
            <xmin>145.38521</xmin>
            <ymin>118.077065</ymin>
            <xmax>276.60455</xmax>
            <ymax>263.1747</ymax>
        </bndbox>
    </object>    <object>
        <name>person</name>
        <pose>Unspecified</pose>
        <truncated>0</truncated>
        <difficult>0.30076158</difficult>
        <bndbox>
            <xmin>289.6429</xmin>
            <ymin>132.85693</ymin>
            <xmax>339.7665</xmax>
            <ymax>182.64589</ymax>
        </bndbox>
    </object>    <object>
        <name>person</name>
        <pose>Unspecified</pose>
        <truncated>0</truncated>
        <difficult>0.271405</difficult>
        <bndbox>
            <xmin>231.87563</xmin>
            <ymin>145.42082</ymin>
            <xmax>261.13666</xmax>
            <ymax>237.05127</ymax>
        </bndbox>
    </object>    <object>
        <name>motorcycle</name>
        <pose>Unspecified</pose>
        <truncated>0</truncated>
        <difficult>0.24428985</difficult>
        <bndbox>
            <xmin>286.47214</xmin>
            <ymin>226.85234</ymin>
            <xmax>353.2809</xmax>
            <ymax>312.0948</ymax>
        </bndbox>
    </object>    <object>
        <name>person</name>
        <pose>Unspecified</pose>
        <truncated>0</truncated>
        <difficult>0.2330449</difficult>
        <bndbox>
            <xmin>328.7765</xmin>
            <ymin>146.1005</ymin>
            <xmax>362.00198</xmax>
            <ymax>206.01422</ymax>
        </bndbox>
    </object>    <object>
        <name>person</name>
        <pose>Unspecified</pose>
        <truncated>0</truncated>
        <difficult>0.22030789</difficult>
        <bndbox>
            <xmin>336.4493</xmin>
            <ymin>154.28241</ymin>
            <xmax>380.65024</xmax>
            <ymax>207.94818</ymax>
        </bndbox>
    </object>    <object>
        <name>car</name>
        <pose>Unspecified</pose>
        <truncated>0</truncated>
        <difficult>0.21033448</difficult>
        <bndbox>
            <xmin>399.12213</xmin>
            <ymin>157.46332</ymin>
            <xmax>466.40335</xmax>
            <ymax>208.85007</ymax>
        </bndbox>
    </object>    <object>
        <name>motorcycle</name>
        <pose>Unspecified</pose>
        <truncated>0</truncated>
        <difficult>0.20826012</difficult>
        <bndbox>
            <xmin>265.15176</xmin>
            <ymin>165.53618</ymin>
            <xmax>353.06555</xmax>
            <ymax>277.3717</ymax>
        </bndbox>
    </object>    <object>
        <name>car</name>
        <pose>Unspecified</pose>
        <truncated>0</truncated>
        <difficult>0.2081624</difficult>
        <bndbox>
            <xmin>286.81488</xmin>
            <ymin>138.85823</ymin>
            <xmax>357.3143</xmax>
            <ymax>196.35121</ymax>
        </bndbox>
    </object>    <object>
        <name>backpack</name>
        <pose>Unspecified</pose>
        <truncated>0</truncated>
        <difficult>0.20062837</difficult>
        <bndbox>
            <xmin>292.72543</xmin>
            <ymin>142.08284</ymin>
            <xmax>343.47833</xmax>
            <ymax>183.68237</ymax>
        </bndbox>
    </object>    <object>
        <name>motorcycle</name>
        <pose>Unspecified</pose>
        <truncated>0</truncated>
        <difficult>0.19834876</difficult>
        <bndbox>
            <xmin>287.32733</xmin>
            <ymin>131.65054</ymin>
            <xmax>351.99194</xmax>
            <ymax>241.67876</ymax>
        </bndbox>
    </object>    <object>
        <name>backpack</name>
        <pose>Unspecified</pose>
        <truncated>0</truncated>
        <difficult>0.19406933</difficult>
        <bndbox>
            <xmin>304.21008</xmin>
            <ymin>152.07881</ymin>
            <xmax>338.25046</xmax>
            <ymax>180.09874</ymax>
        </bndbox>
    </object>    <object>
        <name>person</name>
        <pose>Unspecified</pose>
        <truncated>0</truncated>
        <difficult>0.18463326</difficult>
        <bndbox>
            <xmin>234.21037</xmin>
            <ymin>149.79266</ymin>
            <xmax>255.14206</xmax>
            <ymax>204.45793</ymax>
        </bndbox>
    </object>    <object>
        <name>car</name>
        <pose>Unspecified</pose>
        <truncated>0</truncated>
        <difficult>0.1817154</difficult>
        <bndbox>
            <xmin>271.75714</xmin>
            <ymin>138.5449</ymin>
            <xmax>392.64322</xmax>
            <ymax>223.47273</ymax>
        </bndbox>
    </object>    <object>
        <name>car</name>
        <pose>Unspecified</pose>
        <truncated>0</truncated>
        <difficult>0.16323483</difficult>
        <bndbox>
            <xmin>279.06592</xmin>
            <ymin>166.51425</ymin>
            <xmax>360.40817</xmax>
            <ymax>300.89032</ymax>
        </bndbox>
    </object>    <object>
        <name>person</name>
        <pose>Unspecified</pose>
        <truncated>0</truncated>
        <difficult>0.15698478</difficult>
        <bndbox>
            <xmin>47.489155</xmin>
            <ymin>114.56828</ymin>
            <xmax>64.3137</xmax>
            <ymax>147.20294</ymax>
        </bndbox>
    </object>    <object>
        <name>motorcycle</name>
        <pose>Unspecified</pose>
        <truncated>0</truncated>
        <difficult>0.15478745</difficult>
        <bndbox>
            <xmin>293.65546</xmin>
            <ymin>247.46088</ymin>
            <xmax>329.67728</xmax>
            <ymax>313.41718</ymax>
        </bndbox>
    </object>    <object>
        <name>parking meter</name>
        <pose>Unspecified</pose>
        <truncated>0</truncated>
        <difficult>0.15464377</difficult>
        <bndbox>
            <xmin>172.94667</xmin>
            <ymin>166.42531</ymin>
            <xmax>195.6485</xmax>
            <ymax>222.80727</ymax>
        </bndbox>
    </object>    <object>
        <name>backpack</name>
        <pose>Unspecified</pose>
        <truncated>0</truncated>
        <difficult>0.14975977</difficult>
        <bndbox>
            <xmin>290.40256</xmin>
            <ymin>204.86331</ymin>
            <xmax>343.5202</xmax>
            <ymax>244.26921</ymax>
        </bndbox>
    </object>    <object>
        <name>traffic light</name>
        <pose>Unspecified</pose>
        <truncated>0</truncated>
        <difficult>0.14882898</difficult>
        <bndbox>
            <xmin>345.42664</xmin>
            <ymin>97.63895</ymin>
            <xmax>363.248</xmax>
            <ymax>123.29939</ymax>
        </bndbox>
    </object>    <object>
        <name>truck</name>
        <pose>Unspecified</pose>
        <truncated>0</truncated>
        <difficult>0.14417323</difficult>
        <bndbox>
            <xmin>286.88892</xmin>
            <ymin>134.5221</ymin>
            <xmax>386.09488</xmax>
            <ymax>206.0385</ymax>
        </bndbox>
    </object>    <object>
        <name>person</name>
        <pose>Unspecified</pose>
        <truncated>0</truncated>
        <difficult>0.14071915</difficult>
        <bndbox>
            <xmin>163.20859</xmin>
            <ymin>206.11748</ymin>
            <xmax>194.8644</xmax>
            <ymax>263.47507</ymax>
        </bndbox>
    </object>    <object>
        <name>car</name>
        <pose>Unspecified</pose>
        <truncated>0</truncated>
        <difficult>0.13806635</difficult>
        <bndbox>
            <xmin>287.32733</xmin>
            <ymin>131.65054</ymin>
            <xmax>351.99194</xmax>
            <ymax>241.67876</ymax>
        </bndbox>
    </object>    <object>
        <name>motorcycle</name>
        <pose>Unspecified</pose>
        <truncated>0</truncated>
        <difficult>0.13443539</difficult>
        <bndbox>
            <xmin>280.47473</xmin>
            <ymin>184.7504</ymin>
            <xmax>306.1355</xmax>
            <ymax>201.95367</ymax>
        </bndbox>
    </object>    <object>
        <name>backpack</name>
        <pose>Unspecified</pose>
        <truncated>0</truncated>
        <difficult>0.1305494</difficult>
        <bndbox>
            <xmin>336.52176</xmin>
            <ymin>219.4437</ymin>
            <xmax>360.2815</xmax>
            <ymax>296.14908</ymax>
        </bndbox>
    </object>    <object>
        <name>motorcycle</name>
        <pose>Unspecified</pose>
        <truncated>0</truncated>
        <difficult>0.13025293</difficult>
        <bndbox>
            <xmin>268.5799</xmin>
            <ymin>162.9517</ymin>
            <xmax>350.7621</xmax>
            <ymax>225.07025</ymax>
        </bndbox>
    </object>    <object>
        <name>suitcase</name>
        <pose>Unspecified</pose>
        <truncated>0</truncated>
        <difficult>0.12994933</difficult>
        <bndbox>
            <xmin>172.79181</xmin>
            <ymin>167.04718</ymin>
            <xmax>195.4738</xmax>
            <ymax>220.8954</ymax>
        </bndbox>
    </object>    <object>
        <name>traffic light</name>
        <pose>Unspecified</pose>
        <truncated>0</truncated>
        <difficult>0.12886205</difficult>
        <bndbox>
            <xmin>378.36642</xmin>
            <ymin>103.813866</ymin>
            <xmax>395.3193</xmax>
            <ymax>127.379265</ymax>
        </bndbox>
    </object>    <object>
        <name>person</name>
        <pose>Unspecified</pose>
        <truncated>0</truncated>
        <difficult>0.12835974</difficult>
        <bndbox>
            <xmin>318.3881</xmin>
            <ymin>135.43594</ymin>
            <xmax>352.7133</xmax>
            <ymax>199.1227</ymax>
        </bndbox>
    </object>    <object>
        <name>person</name>
        <pose>Unspecified</pose>
        <truncated>0</truncated>
        <difficult>0.123915136</difficult>
        <bndbox>
            <xmin>48.415016</xmin>
            <ymin>115.24139</ymin>
            <xmax>59.75579</xmax>
            <ymax>136.20593</ymax>
        </bndbox>
    </object>    <object>
        <name>backpack</name>
        <pose>Unspecified</pose>
        <truncated>0</truncated>
        <difficult>0.12171796</difficult>
        <bndbox>
            <xmin>288.62274</xmin>
            <ymin>133.9825</ymin>
            <xmax>353.51355</xmax>
            <ymax>201.64378</ymax>
        </bndbox>
    </object>    <object>
        <name>truck</name>
        <pose>Unspecified</pose>
        <truncated>0</truncated>
        <difficult>0.12105307</difficult>
        <bndbox>
            <xmin>377.0235</xmin>
            <ymin>162.49817</ymin>
            <xmax>420.36853</xmax>
            <ymax>196.65935</ymax>
        </bndbox>
    </object>    <object>
        <name>truck</name>
        <pose>Unspecified</pose>
        <truncated>0</truncated>
        <difficult>0.117563665</difficult>
        <bndbox>
            <xmin>338.18903</xmin>
            <ymin>156.67897</ymin>
            <xmax>383.8909</xmax>
            <ymax>209.8288</ymax>
        </bndbox>
    </object>    <object>
        <name>suitcase</name>
        <pose>Unspecified</pose>
        <truncated>0</truncated>
        <difficult>0.11710635</difficult>
        <bndbox>
            <xmin>290.30112</xmin>
            <ymin>204.77849</ymin>
            <xmax>343.38876</xmax>
            <ymax>244.55469</ymax>
        </bndbox>
    </object>    <object>
        <name>person</name>
        <pose>Unspecified</pose>
        <truncated>0</truncated>
        <difficult>0.11507028</difficult>
        <bndbox>
            <xmin>333.47293</xmin>
            <ymin>148.63983</ymin>
            <xmax>353.20975</xmax>
            <ymax>194.24942</ymax>
        </bndbox>
    </object>    <object>
        <name>person</name>
        <pose>Unspecified</pose>
        <truncated>0</truncated>
        <difficult>0.11447668</difficult>
        <bndbox>
            <xmin>131.29883</xmin>
            <ymin>187.30994</ymin>
            <xmax>145.74548</xmax>
            <ymax>236.09991</ymax>
        </bndbox>
    </object>    <object>
        <name>person</name>
        <pose>Unspecified</pose>
        <truncated>0</truncated>
        <difficult>0.10997823</difficult>
        <bndbox>
            <xmin>298.33032</xmin>
            <ymin>147.36882</ymin>
            <xmax>354.2721</xmax>
            <ymax>183.51305</ymax>
        </bndbox>
    </object>    <object>
        <name>motorcycle</name>
        <pose>Unspecified</pose>
        <truncated>0</truncated>
        <difficult>0.108335674</difficult>
        <bndbox>
            <xmin>283.19522</xmin>
            <ymin>139.7224</ymin>
            <xmax>350.2418</xmax>
            <ymax>192.90747</ymax>
        </bndbox>
    </object>    <object>
        <name>car</name>
        <pose>Unspecified</pose>
        <truncated>0</truncated>
        <difficult>0.10800406</difficult>
        <bndbox>
            <xmin>356.07858</xmin>
            <ymin>157.08295</ymin>
            <xmax>385.988</xmax>
            <ymax>200.70622</ymax>
        </bndbox>
    </object>    <object>
        <name>remote</name>
        <pose>Unspecified</pose>
        <truncated>0</truncated>
        <difficult>0.10702467</difficult>
        <bndbox>
            <xmin>180.57155</xmin>
            <ymin>166.09308</ymin>
            <xmax>190.83456</xmax>
            <ymax>175.08276</ymax>
        </bndbox>
    </object>    <object>
        <name>backpack</name>
        <pose>Unspecified</pose>
        <truncated>0</truncated>
        <difficult>0.10644364</difficult>
        <bndbox>
            <xmin>172.87111</xmin>
            <ymin>165.26413</ymin>
            <xmax>195.38857</xmax>
            <ymax>221.09898</ymax>
        </bndbox>
    </object>    <object>
        <name>person</name>
        <pose>Unspecified</pose>
        <truncated>0</truncated>
        <difficult>0.105664015</difficult>
        <bndbox>
            <xmin>209.00491</xmin>
            <ymin>134.46678</ymin>
            <xmax>262.47336</xmax>
            <ymax>258.2434</ymax>
        </bndbox>
    </object>    <object>
        <name>person</name>
        <pose>Unspecified</pose>
        <truncated>0</truncated>
        <difficult>0.103342384</difficult>
        <bndbox>
            <xmin>289.66977</xmin>
            <ymin>158.0013</ymin>
            <xmax>348.45142</xmax>
            <ymax>266.5118</ymax>
        </bndbox>
    </object>    <object>
        <name>person</name>
        <pose>Unspecified</pose>
        <truncated>0</truncated>
        <difficult>0.1029138</difficult>
        <bndbox>
            <xmin>273.96625</xmin>
            <ymin>143.10208</ymin>
            <xmax>338.06137</xmax>
            <ymax>194.07988</ymax>
        </bndbox>
    </object>    <object>
        <name>truck</name>
        <pose>Unspecified</pose>
        <truncated>0</truncated>
        <difficult>0.102324486</difficult>
        <bndbox>
            <xmin>179.3983</xmin>
            <ymin>119.839676</ymin>
            <xmax>362.96814</xmax>
            <ymax>278.19662</ymax>
        </bndbox>
    </object>    <object>
        <name>cell phone</name>
        <pose>Unspecified</pose>
        <truncated>0</truncated>
        <difficult>0.10201675</difficult>
        <bndbox>
            <xmin>172.38818</xmin>
            <ymin>166.3267</ymin>
            <xmax>195.80681</xmax>
            <ymax>220.81248</ymax>
        </bndbox>
    </object>    <object>
        <name>car</name>
        <pose>Unspecified</pose>
        <truncated>0</truncated>
        <difficult>0.10196695</difficult>
        <bndbox>
            <xmin>367.93518</xmin>
            <ymin>160.30104</ymin>
            <xmax>391.82965</xmax>
            <ymax>201.43565</ymax>
        </bndbox>
    </object>    <object>
        <name>person</name>
        <pose>Unspecified</pose>
        <truncated>0</truncated>
        <difficult>0.100138396</difficult>
        <bndbox>
            <xmin>34.429565</xmin>
            <ymin>105.14471</ymin>
            <xmax>73.583885</xmax>
            <ymax>189.04422</ymax>
        </bndbox>
    </object>    <object>
        <name>truck</name>
        <pose>Unspecified</pose>
        <truncated>0</truncated>
        <difficult>0.097452015</difficult>
        <bndbox>
            <xmin>419.31903</xmin>
            <ymin>154.36093</ymin>
            <xmax>481.16248</xmax>
            <ymax>216.4567</ymax>
        </bndbox>
    </object>    <object>
        <name>motorcycle</name>
        <pose>Unspecified</pose>
        <truncated>0</truncated>
        <difficult>0.097172886</difficult>
        <bndbox>
            <xmin>272.88287</xmin>
            <ymin>171.52393</ymin>
            <xmax>339.8333</xmax>
            <ymax>202.31657</ymax>
        </bndbox>
    </object>    <object>
        <name>mouse</name>
        <pose>Unspecified</pose>
        <truncated>0</truncated>
        <difficult>0.096986145</difficult>
        <bndbox>
            <xmin>181.05905</xmin>
            <ymin>165.97969</ymin>
            <xmax>191.07921</xmax>
            <ymax>175.50449</ymax>
        </bndbox>
    </object>    <object>
        <name>backpack</name>
        <pose>Unspecified</pose>
        <truncated>0</truncated>
        <difficult>0.09634131</difficult>
        <bndbox>
            <xmin>276.6591</xmin>
            <ymin>163.79099</ymin>
            <xmax>362.35522</xmax>
            <ymax>296.07</ymax>
        </bndbox>
    </object>    <object>
        <name>backpack</name>
        <pose>Unspecified</pose>
        <truncated>0</truncated>
        <difficult>0.09535721</difficult>
        <bndbox>
            <xmin>315.99075</xmin>
            <ymin>153.90045</ymin>
            <xmax>336.71378</xmax>
            <ymax>176.61638</ymax>
        </bndbox>
    </object>    <object>
        <name>motorcycle</name>
        <pose>Unspecified</pose>
        <truncated>0</truncated>
        <difficult>0.094593525</difficult>
        <bndbox>
            <xmin>285.10156</xmin>
            <ymin>239.157</ymin>
            <xmax>325.7247</xmax>
            <ymax>296.0273</ymax>
        </bndbox>
    </object>    <object>
        <name>person</name>
        <pose>Unspecified</pose>
        <truncated>0</truncated>
        <difficult>0.09402257</difficult>
        <bndbox>
            <xmin>273.51648</xmin>
            <ymin>152.72874</ymin>
            <xmax>380.191</xmax>
            <ymax>213.21178</ymax>
        </bndbox>
    </object>    <object>
        <name>car</name>
        <pose>Unspecified</pose>
        <truncated>0</truncated>
        <difficult>0.09386486</difficult>
        <bndbox>
            <xmin>394.86478</xmin>
            <ymin>166.12074</ymin>
            <xmax>424.67953</xmax>
            <ymax>192.58145</ymax>
        </bndbox>
    </object>    <object>
        <name>backpack</name>
        <pose>Unspecified</pose>
        <truncated>0</truncated>
        <difficult>0.09322581</difficult>
        <bndbox>
            <xmin>313.74155</xmin>
            <ymin>145.73682</ymin>
            <xmax>346.60446</xmax>
            <ymax>177.54611</ymax>
        </bndbox>
    </object>    <object>
        <name>motorcycle</name>
        <pose>Unspecified</pose>
        <truncated>0</truncated>
        <difficult>0.09245688</difficult>
        <bndbox>
            <xmin>9.140734</xmin>
            <ymin>203.63849</ymin>
            <xmax>64.08227</xmax>
            <ymax>250.59622</ymax>
        </bndbox>
    </object>    <object>
        <name>suitcase</name>
        <pose>Unspecified</pose>
        <truncated>0</truncated>
        <difficult>0.091703594</difficult>
        <bndbox>
            <xmin>284.9333</xmin>
            <ymin>208.91805</ymin>
            <xmax>295.69403</xmax>
            <ymax>238.14124</ymax>
        </bndbox>
    </object>    <object>
        <name>hair drier</name>
        <pose>Unspecified</pose>
        <truncated>0</truncated>
        <difficult>0.09143111</difficult>
        <bndbox>
            <xmin>180.57155</xmin>
            <ymin>166.09308</ymin>
            <xmax>190.83456</xmax>
            <ymax>175.08276</ymax>
        </bndbox>
    </object>    <object>
        <name>handbag</name>
        <pose>Unspecified</pose>
        <truncated>0</truncated>
        <difficult>0.09097457</difficult>
        <bndbox>
            <xmin>290.30112</xmin>
            <ymin>204.77849</ymin>
            <xmax>343.38876</xmax>
            <ymax>244.55469</ymax>
        </bndbox>
    </object>    <object>
        <name>person</name>
        <pose>Unspecified</pose>
        <truncated>0</truncated>
        <difficult>0.090574</difficult>
        <bndbox>
            <xmin>1.1801233</xmin>
            <ymin>134.27603</ymin>
            <xmax>49.709507</xmax>
            <ymax>214.25095</ymax>
        </bndbox>
    </object>    <object>
        <name>car</name>
        <pose>Unspecified</pose>
        <truncated>0</truncated>
        <difficult>0.090358734</difficult>
        <bndbox>
            <xmin>312.31183</xmin>
            <ymin>151.21234</ymin>
            <xmax>435.55563</xmax>
            <ymax>216.08167</ymax>
        </bndbox>
    </object>    <object>
        <name>motorcycle</name>
        <pose>Unspecified</pose>
        <truncated>0</truncated>
        <difficult>0.09006199</difficult>
        <bndbox>
            <xmin>134.94777</xmin>
            <ymin>189.6524</ymin>
            <xmax>263.8168</xmax>
            <ymax>265.39673</ymax>
        </bndbox>
    </object>    <object>
        <name>backpack</name>
        <pose>Unspecified</pose>
        <truncated>0</truncated>
        <difficult>0.08978903</difficult>
        <bndbox>
            <xmin>320.48505</xmin>
            <ymin>144.1863</ymin>
            <xmax>356.73798</xmax>
            <ymax>201.14745</ymax>
        </bndbox>
    </object>    <object>
        <name>bus</name>
        <pose>Unspecified</pose>
        <truncated>0</truncated>
        <difficult>0.08936182</difficult>
        <bndbox>
            <xmin>146.21764</xmin>
            <ymin>116.26175</ymin>
            <xmax>260.60294</xmax>
            <ymax>182.16164</ymax>
        </bndbox>
    </object>    <object>
        <name>backpack</name>
        <pose>Unspecified</pose>
        <truncated>0</truncated>
        <difficult>0.08934721</difficult>
        <bndbox>
            <xmin>309.3887</xmin>
            <ymin>150.22871</ymin>
            <xmax>333.87717</xmax>
            <ymax>170.05077</ymax>
        </bndbox>
    </object>    <object>
        <name>person</name>
        <pose>Unspecified</pose>
        <truncated>0</truncated>
        <difficult>0.08915016</difficult>
        <bndbox>
            <xmin>3.1562457</xmin>
            <ymin>109.869225</ymin>
            <xmax>52.92647</xmax>
            <ymax>183.82162</ymax>
        </bndbox>
    </object>    <object>
        <name>train</name>
        <pose>Unspecified</pose>
        <truncated>0</truncated>
        <difficult>0.08728215</difficult>
        <bndbox>
            <xmin>144.37027</xmin>
            <ymin>111.67042</ymin>
            <xmax>275.53668</xmax>
            <ymax>264.33835</ymax>
        </bndbox>
    </object>    <object>
        <name>person</name>
        <pose>Unspecified</pose>
        <truncated>0</truncated>
        <difficult>0.08693239</difficult>
        <bndbox>
            <xmin>40.011024</xmin>
            <ymin>152.24298</ymin>
            <xmax>69.57371</xmax>
            <ymax>220.62173</ymax>
        </bndbox>
    </object>    <object>
        <name>traffic light</name>
        <pose>Unspecified</pose>
        <truncated>0</truncated>
        <difficult>0.085730314</difficult>
        <bndbox>
            <xmin>399.9063</xmin>
            <ymin>117.00764</ymin>
            <xmax>413.65134</xmax>
            <ymax>136.97282</ymax>
        </bndbox>
    </object>    <object>
        <name>backpack</name>
        <pose>Unspecified</pose>
        <truncated>0</truncated>
        <difficult>0.08561978</difficult>
        <bndbox>
            <xmin>284.58322</xmin>
            <ymin>206.13873</ymin>
            <xmax>296.56146</xmax>
            <ymax>238.02663</ymax>
        </bndbox>
    </object>    <object>
        <name>person</name>
        <pose>Unspecified</pose>
        <truncated>0</truncated>
        <difficult>0.08527717</difficult>
        <bndbox>
            <xmin>173.23749</xmin>
            <ymin>163.85115</ymin>
            <xmax>195.53308</xmax>
            <ymax>219.7966</ymax>
        </bndbox>
    </object>    <object>
        <name>car</name>
        <pose>Unspecified</pose>
        <truncated>0</truncated>
        <difficult>0.08391568</difficult>
        <bndbox>
            <xmin>382.66174</xmin>
            <ymin>172.71573</ymin>
            <xmax>414.81552</xmax>
            <ymax>191.26465</ymax>
        </bndbox>
    </object>    <object>
        <name>person</name>
        <pose>Unspecified</pose>
        <truncated>0</truncated>
        <difficult>0.08365643</difficult>
        <bndbox>
            <xmin>240.7022</xmin>
            <ymin>149.52513</ymin>
            <xmax>255.26381</xmax>
            <ymax>183.98668</ymax>
        </bndbox>
    </object>    <object>
        <name>motorcycle</name>
        <pose>Unspecified</pose>
        <truncated>0</truncated>
        <difficult>0.083550304</difficult>
        <bndbox>
            <xmin>298.55078</xmin>
            <ymin>157.57614</ymin>
            <xmax>394.9333</xmax>
            <ymax>274.57117</ymax>
        </bndbox>
    </object>    <object>
        <name>suitcase</name>
        <pose>Unspecified</pose>
        <truncated>0</truncated>
        <difficult>0.0835152</difficult>
        <bndbox>
            <xmin>281.1537</xmin>
            <ymin>147.34961</ymin>
            <xmax>377.46356</xmax>
            <ymax>208.93782</ymax>
        </bndbox>
    </object>    <object>
        <name>traffic light</name>
        <pose>Unspecified</pose>
        <truncated>0</truncated>
        <difficult>0.083441496</difficult>
        <bndbox>
            <xmin>387.7555</xmin>
            <ymin>105.275826</ymin>
            <xmax>395.91995</xmax>
            <ymax>126.67911</ymax>
        </bndbox>
    </object>    <object>
        <name>car</name>
        <pose>Unspecified</pose>
        <truncated>0</truncated>
        <difficult>0.08334574</difficult>
        <bndbox>
            <xmin>326.57965</xmin>
            <ymin>150.22299</ymin>
            <xmax>368.6576</xmax>
            <ymax>202.21475</ymax>
        </bndbox>
    </object>    <object>
        <name>car</name>
        <pose>Unspecified</pose>
        <truncated>0</truncated>
        <difficult>0.08313188</difficult>
        <bndbox>
            <xmin>306.26346</xmin>
            <ymin>154.65515</ymin>
            <xmax>373.4419</xmax>
            <ymax>255.26582</ymax>
        </bndbox>
    </object>    <object>
        <name>car</name>
        <pose>Unspecified</pose>
        <truncated>0</truncated>
        <difficult>0.0827775</difficult>
        <bndbox>
            <xmin>179.3983</xmin>
            <ymin>119.839676</ymin>
            <xmax>362.96814</xmax>
            <ymax>278.19662</ymax>
        </bndbox>
    </object>    <object>
        <name>kite</name>
        <pose>Unspecified</pose>
        <truncated>0</truncated>
        <difficult>0.08234316</difficult>
        <bndbox>
            <xmin>345.42664</xmin>
            <ymin>97.63895</ymin>
            <xmax>363.248</xmax>
            <ymax>123.29939</ymax>
        </bndbox>
    </object>    <object>
        <name>skis</name>
        <pose>Unspecified</pose>
        <truncated>0</truncated>
        <difficult>0.08206949</difficult>
        <bndbox>
            <xmin>280.1237</xmin>
            <ymin>146.97205</ymin>
            <xmax>377.6115</xmax>
            <ymax>208.64174</ymax>
        </bndbox>
    </object>    <object>
        <name>car</name>
        <pose>Unspecified</pose>
        <truncated>0</truncated>
        <difficult>0.08190513</difficult>
        <bndbox>
            <xmin>310.69406</xmin>
            <ymin>157.14075</ymin>
            <xmax>352.46564</xmax>
            <ymax>220.81583</ymax>
        </bndbox>
    </object>    <object>
        <name>person</name>
        <pose>Unspecified</pose>
        <truncated>0</truncated>
        <difficult>0.08162221</difficult>
        <bndbox>
            <xmin>167.54222</xmin>
            <ymin>140.50545</ymin>
            <xmax>187.06206</xmax>
            <ymax>166.12106</ymax>
        </bndbox>
    </object>    <object>
        <name>car</name>
        <pose>Unspecified</pose>
        <truncated>0</truncated>
        <difficult>0.08106989</difficult>
        <bndbox>
            <xmin>134.94777</xmin>
            <ymin>189.6524</ymin>
            <xmax>263.8168</xmax>
            <ymax>265.39673</ymax>
        </bndbox>
    </object>    <object>
        <name>backpack</name>
        <pose>Unspecified</pose>
        <truncated>0</truncated>
        <difficult>0.08063972</difficult>
        <bndbox>
            <xmin>332.06525</xmin>
            <ymin>157.20647</ymin>
            <xmax>345.48462</xmax>
            <ymax>186.58136</ymax>
        </bndbox>
    </object>    <object>
        <name>handbag</name>
        <pose>Unspecified</pose>
        <truncated>0</truncated>
        <difficult>0.08045688</difficult>
        <bndbox>
            <xmin>284.42703</xmin>
            <ymin>207.87712</ymin>
            <xmax>296.6168</xmax>
            <ymax>238.22299</ymax>
        </bndbox>
    </object>    <object>
        <name>backpack</name>
        <pose>Unspecified</pose>
        <truncated>0</truncated>
        <difficult>0.08032814</difficult>
        <bndbox>
            <xmin>237.32797</xmin>
            <ymin>151.05855</ymin>
            <xmax>258.51428</xmax>
            <ymax>204.26869</ymax>
        </bndbox>
    </object>    <object>
        <name>person</name>
        <pose>Unspecified</pose>
        <truncated>0</truncated>
        <difficult>0.08015221</difficult>
        <bndbox>
            <xmin>224.69589</xmin>
            <ymin>148.47438</ymin>
            <xmax>251.6066</xmax>
            <ymax>244.71353</ymax>
        </bndbox>
    </object>    <object>
        <name>person</name>
        <pose>Unspecified</pose>
        <truncated>0</truncated>
        <difficult>0.079764605</difficult>
        <bndbox>
            <xmin>16.203703</xmin>
            <ymin>108.30296</ymin>
            <xmax>53.862434</xmax>
            <ymax>152.50224</ymax>
        </bndbox>
    </object>    <object>
        <name>car</name>
        <pose>Unspecified</pose>
        <truncated>0</truncated>
        <difficult>0.07827625</difficult>
        <bndbox>
            <xmin>353.67746</xmin>
            <ymin>156.56516</ymin>
            <xmax>453.96417</xmax>
            <ymax>211.11224</ymax>
        </bndbox>
    </object>    <object>
        <name>handbag</name>
        <pose>Unspecified</pose>
        <truncated>0</truncated>
        <difficult>0.077730924</difficult>
        <bndbox>
            <xmin>338.02606</xmin>
            <ymin>214.09799</ymin>
            <xmax>360.25296</xmax>
            <ymax>285.57214</ymax>
        </bndbox>
    </object>    <object>
        <name>clock</name>
        <pose>Unspecified</pose>
        <truncated>0</truncated>
        <difficult>0.07753864</difficult>
        <bndbox>
            <xmin>180.57155</xmin>
            <ymin>166.09308</ymin>
            <xmax>190.83456</xmax>
            <ymax>175.08276</ymax>
        </bndbox>
    </object>    <object>
        <name>backpack</name>
        <pose>Unspecified</pose>
        <truncated>0</truncated>
        <difficult>0.07705352</difficult>
        <bndbox>
            <xmin>334.93744</xmin>
            <ymin>156.31915</ymin>
            <xmax>351.41626</xmax>
            <ymax>189.26897</ymax>
        </bndbox>
    </object>    <object>
        <name>backpack</name>
        <pose>Unspecified</pose>
        <truncated>0</truncated>
        <difficult>0.07692045</difficult>
        <bndbox>
            <xmin>301.67786</xmin>
            <ymin>151.39635</ymin>
            <xmax>359.8144</xmax>
            <ymax>188.98921</ymax>
        </bndbox>
    </object>    <object>
        <name>person</name>
        <pose>Unspecified</pose>
        <truncated>0</truncated>
        <difficult>0.0767768</difficult>
        <bndbox>
            <xmin>53.779003</xmin>
            <ymin>128.59053</ymin>
            <xmax>69.113716</xmax>
            <ymax>169.32999</ymax>
        </bndbox>
    </object>    <object>
        <name>motorcycle</name>
        <pose>Unspecified</pose>
        <truncated>0</truncated>
        <difficult>0.076487154</difficult>
        <bndbox>
            <xmin>272.29385</xmin>
            <ymin>170.01306</ymin>
            <xmax>303.0102</xmax>
            <ymax>202.06807</ymax>
        </bndbox>
    </object>    <object>
        <name>cell phone</name>
        <pose>Unspecified</pose>
        <truncated>0</truncated>
        <difficult>0.07644221</difficult>
        <bndbox>
            <xmin>180.57155</xmin>
            <ymin>166.09308</ymin>
            <xmax>190.83456</xmax>
            <ymax>175.08276</ymax>
        </bndbox>
    </object>    <object>
        <name>person</name>
        <pose>Unspecified</pose>
        <truncated>0</truncated>
        <difficult>0.07622525</difficult>
        <bndbox>
            <xmin>13.98826</xmin>
            <ymin>127.91799</ymin>
            <xmax>67.09691</xmax>
            <ymax>169.71172</ymax>
        </bndbox>
    </object>    <object>
        <name>backpack</name>
        <pose>Unspecified</pose>
        <truncated>0</truncated>
        <difficult>0.07578707</difficult>
        <bndbox>
            <xmin>282.743</xmin>
            <ymin>147.61377</ymin>
            <xmax>370.40756</xmax>
            <ymax>223.89085</ymax>
        </bndbox>
    </object>    <object>
        <name>car</name>
        <pose>Unspecified</pose>
        <truncated>0</truncated>
        <difficult>0.07517865</difficult>
        <bndbox>
            <xmin>410.54416</xmin>
            <ymin>165.36092</ymin>
            <xmax>427.57898</xmax>
            <ymax>193.89946</ymax>
        </bndbox>
    </object>    <object>
        <name>truck</name>
        <pose>Unspecified</pose>
        <truncated>0</truncated>
        <difficult>0.07514903</difficult>
        <bndbox>
            <xmin>277.57645</xmin>
            <ymin>167.19916</ymin>
            <xmax>359.83612</xmax>
            <ymax>305.552</ymax>
        </bndbox>
    </object>    <object>
        <name>backpack</name>
        <pose>Unspecified</pose>
        <truncated>0</truncated>
        <difficult>0.07511479</difficult>
        <bndbox>
            <xmin>325.37082</xmin>
            <ymin>157.33183</ymin>
            <xmax>342.37555</xmax>
            <ymax>181.34323</ymax>
        </bndbox>
    </object>    <object>
        <name>car</name>
        <pose>Unspecified</pose>
        <truncated>0</truncated>
        <difficult>0.074849814</difficult>
        <bndbox>
            <xmin>365.17346</xmin>
            <ymin>165.95331</ymin>
            <xmax>426.32474</xmax>
            <ymax>208.00076</ymax>
        </bndbox>
    </object>    <object>
        <name>person</name>
        <pose>Unspecified</pose>
        <truncated>0</truncated>
        <difficult>0.074561894</difficult>
        <bndbox>
            <xmin>310.69406</xmin>
            <ymin>157.14075</ymin>
            <xmax>352.46564</xmax>
            <ymax>220.81583</ymax>
        </bndbox>
    </object>    <object>
        <name>bus</name>
        <pose>Unspecified</pose>
        <truncated>0</truncated>
        <difficult>0.074341506</difficult>
        <bndbox>
            <xmin>286.88892</xmin>
            <ymin>134.5221</ymin>
            <xmax>386.09488</xmax>
            <ymax>206.0385</ymax>
        </bndbox>
    </object>    <object>
        <name>traffic light</name>
        <pose>Unspecified</pose>
        <truncated>0</truncated>
        <difficult>0.07395023</difficult>
        <bndbox>
            <xmin>406.41458</xmin>
            <ymin>117.725204</ymin>
            <xmax>415.55588</xmax>
            <ymax>136.88405</ymax>
        </bndbox>
    </object>    <object>
        <name>backpack</name>
        <pose>Unspecified</pose>
        <truncated>0</truncated>
        <difficult>0.07368037</difficult>
        <bndbox>
            <xmin>341.41205</xmin>
            <ymin>231.63658</ymin>
            <xmax>358.75314</xmax>
            <ymax>281.0769</ymax>
        </bndbox>
    </object>    <object>
        <name>person</name>
        <pose>Unspecified</pose>
        <truncated>0</truncated>
        <difficult>0.07358289</difficult>
        <bndbox>
            <xmin>304.21008</xmin>
            <ymin>152.07881</ymin>
            <xmax>338.25046</xmax>
            <ymax>180.09874</ymax>
        </bndbox>
    </object>    <object>
        <name>car</name>
        <pose>Unspecified</pose>
        <truncated>0</truncated>
        <difficult>0.07345539</difficult>
        <bndbox>
            <xmin>369.93454</xmin>
            <ymin>165.29712</ymin>
            <xmax>384.10938</xmax>
            <ymax>205.8386</ymax>
        </bndbox>
    </object>    <object>
        <name>car</name>
        <pose>Unspecified</pose>
        <truncated>0</truncated>
        <difficult>0.07332155</difficult>
        <bndbox>
            <xmin>229.74445</xmin>
            <ymin>142.19911</ymin>
            <xmax>264.3827</xmax>
            <ymax>248.07205</ymax>
        </bndbox>
    </object>    <object>
        <name>traffic light</name>
        <pose>Unspecified</pose>
        <truncated>0</truncated>
        <difficult>0.07237929</difficult>
        <bndbox>
            <xmin>173.12762</xmin>
            <ymin>166.78963</ymin>
            <xmax>195.569</xmax>
            <ymax>220.00255</ymax>
        </bndbox>
    </object>    <object>
        <name>bicycle</name>
        <pose>Unspecified</pose>
        <truncated>0</truncated>
        <difficult>0.07221004</difficult>
        <bndbox>
            <xmin>293.53506</xmin>
            <ymin>246.17279</ymin>
            <xmax>329.24573</xmax>
            <ymax>313.10828</ymax>
        </bndbox>
    </object>    <object>
        <name>person</name>
        <pose>Unspecified</pose>
        <truncated>0</truncated>
        <difficult>0.071576625</difficult>
        <bndbox>
            <xmin>167.98325</xmin>
            <ymin>206.47815</ymin>
            <xmax>193.39604</xmax>
            <ymax>229.00383</ymax>
        </bndbox>
    </object>    <object>
        <name>suitcase</name>
        <pose>Unspecified</pose>
        <truncated>0</truncated>
        <difficult>0.07031047</difficult>
        <bndbox>
            <xmin>271.61472</xmin>
            <ymin>166.37941</ymin>
            <xmax>286.21658</xmax>
            <ymax>177.96548</ymax>
        </bndbox>
    </object>    <object>
        <name>person</name>
        <pose>Unspecified</pose>
        <truncated>0</truncated>
        <difficult>0.07027757</difficult>
        <bndbox>
            <xmin>369.93454</xmin>
            <ymin>165.29712</ymin>
            <xmax>384.10938</xmax>
            <ymax>205.8386</ymax>
        </bndbox>
    </object>    <object>
        <name>person</name>
        <pose>Unspecified</pose>
        <truncated>0</truncated>
        <difficult>0.07023871</difficult>
        <bndbox>
            <xmin>312.06204</xmin>
            <ymin>153.18149</ymin>
            <xmax>389.9837</xmax>
            <ymax>285.1815</ymax>
        </bndbox>
    </object>    <object>
        <name>cell phone</name>
        <pose>Unspecified</pose>
        <truncated>0</truncated>
        <difficult>0.070138276</difficult>
        <bndbox>
            <xmin>175.17879</xmin>
            <ymin>174.9452</ymin>
            <xmax>193.0308</xmax>
            <ymax>208.6177</ymax>
        </bndbox>
    </object>    <object>
        <name>person</name>
        <pose>Unspecified</pose>
        <truncated>0</truncated>
        <difficult>0.070002615</difficult>
        <bndbox>
            <xmin>323.87537</xmin>
            <ymin>151.76534</ymin>
            <xmax>348.57086</xmax>
            <ymax>181.50417</ymax>
        </bndbox>
    </object>    <object>
        <name>tv</name>
        <pose>Unspecified</pose>
        <truncated>0</truncated>
        <difficult>0.06924865</difficult>
        <bndbox>
            <xmin>345.10452</xmin>
            <ymin>97.109825</ymin>
            <xmax>364.3946</xmax>
            <ymax>124.90644</ymax>
        </bndbox>
    </object>    <object>
        <name>truck</name>
        <pose>Unspecified</pose>
        <truncated>0</truncated>
        <difficult>0.06911641</difficult>
        <bndbox>
            <xmin>200.39384</xmin>
            <ymin>119.51727</ymin>
            <xmax>261.5246</xmax>
            <ymax>245.36517</ymax>
        </bndbox>
    </object>    <object>
        <name>suitcase</name>
        <pose>Unspecified</pose>
        <truncated>0</truncated>
        <difficult>0.068634</difficult>
        <bndbox>
            <xmin>278.76004</xmin>
            <ymin>168.87527</ymin>
            <xmax>358.65784</xmax>
            <ymax>311.2217</ymax>
        </bndbox>
    </object>    <object>
        <name>backpack</name>
        <pose>Unspecified</pose>
        <truncated>0</truncated>
        <difficult>0.06804258</difficult>
        <bndbox>
            <xmin>5.0833945</xmin>
            <ymin>146.55722</ymin>
            <xmax>61.34468</xmax>
            <ymax>227.40758</ymax>
        </bndbox>
    </object>    <object>
        <name>motorcycle</name>
        <pose>Unspecified</pose>
        <truncated>0</truncated>
        <difficult>0.06798276</difficult>
        <bndbox>
            <xmin>272.6556</xmin>
            <ymin>189.55995</ymin>
            <xmax>300.13013</xmax>
            <ymax>202.53363</ymax>
        </bndbox>
    </object>    <object>
        <name>car</name>
        <pose>Unspecified</pose>
        <truncated>0</truncated>
        <difficult>0.06796202</difficult>
        <bndbox>
            <xmin>380.8498</xmin>
            <ymin>165.18568</ymin>
            <xmax>413.02484</xmax>
            <ymax>185.81596</ymax>
        </bndbox>
    </object>    <object>
        <name>remote</name>
        <pose>Unspecified</pose>
        <truncated>0</truncated>
        <difficult>0.06697786</difficult>
        <bndbox>
            <xmin>178.2167</xmin>
            <ymin>166.0206</ymin>
            <xmax>194.02965</xmax>
            <ymax>180.082</ymax>
        </bndbox>
    </object>    <object>
        <name>person</name>
        <pose>Unspecified</pose>
        <truncated>0</truncated>
        <difficult>0.06660855</difficult>
        <bndbox>
            <xmin>171.77394</xmin>
            <ymin>206.5875</ymin>
            <xmax>186.705</xmax>
            <ymax>222.34865</ymax>
        </bndbox>
    </object>    <object>
        <name>motorcycle</name>
        <pose>Unspecified</pose>
        <truncated>0</truncated>
        <difficult>0.0658797</difficult>
        <bndbox>
            <xmin>145.38521</xmin>
            <ymin>118.077065</ymin>
            <xmax>276.60455</xmax>
            <ymax>263.1747</ymax>
        </bndbox>
    </object>    <object>
        <name>person</name>
        <pose>Unspecified</pose>
        <truncated>0</truncated>
        <difficult>0.065561</difficult>
        <bndbox>
            <xmin>167.5591</xmin>
            <ymin>173.25264</ymin>
            <xmax>196.03226</xmax>
            <ymax>242.05005</ymax>
        </bndbox>
    </object>    <object>
        <name>person</name>
        <pose>Unspecified</pose>
        <truncated>0</truncated>
        <difficult>0.06478277</difficult>
        <bndbox>
            <xmin>51.02583</xmin>
            <ymin>134.99205</ymin>
            <xmax>68.41706</xmax>
            <ymax>189.41408</ymax>
        </bndbox>
    </object>    <object>
        <name>person</name>
        <pose>Unspecified</pose>
        <truncated>0</truncated>
        <difficult>0.06464717</difficult>
        <bndbox>
            <xmin>136.74007</xmin>
            <ymin>146.3448</ymin>
            <xmax>148.12811</xmax>
            <ymax>192.76904</ymax>
        </bndbox>
    </object>    <object>
        <name>person</name>
        <pose>Unspecified</pose>
        <truncated>0</truncated>
        <difficult>0.06427458</difficult>
        <bndbox>
            <xmin>229.54016</xmin>
            <ymin>126.697365</ymin>
            <xmax>260.16797</xmax>
            <ymax>199.41722</ymax>
        </bndbox>
    </object>    <object>
        <name>motorcycle</name>
        <pose>Unspecified</pose>
        <truncated>0</truncated>
        <difficult>0.064272195</difficult>
        <bndbox>
            <xmin>6.848295</xmin>
            <ymin>172.15097</ymin>
            <xmax>50.453003</xmax>
            <ymax>222.85312</ymax>
        </bndbox>
    </object>    <object>
        <name>backpack</name>
        <pose>Unspecified</pose>
        <truncated>0</truncated>
        <difficult>0.06424877</difficult>
        <bndbox>
            <xmin>174.86697</xmin>
            <ymin>181.81482</ymin>
            <xmax>193.04301</xmax>
            <ymax>215.9215</ymax>
        </bndbox>
    </object>    <object>
        <name>person</name>
        <pose>Unspecified</pose>
        <truncated>0</truncated>
        <difficult>0.06407282</difficult>
        <bndbox>
            <xmin>149.8599</xmin>
            <ymin>133.54362</ymin>
            <xmax>164.91202</xmax>
            <ymax>164.59056</ymax>
        </bndbox>
    </object>    <object>
        <name>hair drier</name>
        <pose>Unspecified</pose>
        <truncated>0</truncated>
        <difficult>0.06406301</difficult>
        <bndbox>
            <xmin>178.2167</xmin>
            <ymin>166.0206</ymin>
            <xmax>194.02965</xmax>
            <ymax>180.082</ymax>
        </bndbox>
    </object>    <object>
        <name>car</name>
        <pose>Unspecified</pose>
        <truncated>0</truncated>
        <difficult>0.063911915</difficult>
        <bndbox>
            <xmin>284.55377</xmin>
            <ymin>207.25255</ymin>
            <xmax>295.47275</xmax>
            <ymax>237.94934</ymax>
        </bndbox>
    </object>    <object>
        <name>motorcycle</name>
        <pose>Unspecified</pose>
        <truncated>0</truncated>
        <difficult>0.063750714</difficult>
        <bndbox>
            <xmin>229.79791</xmin>
            <ymin>143.30998</ymin>
            <xmax>362.59528</xmax>
            <ymax>303.31744</ymax>
        </bndbox>
    </object>    <object>
        <name>handbag</name>
        <pose>Unspecified</pose>
        <truncated>0</truncated>
        <difficult>0.063667536</difficult>
        <bndbox>
            <xmin>331.49573</xmin>
            <ymin>211.85869</ymin>
            <xmax>343.8029</xmax>
            <ymax>240.83496</ymax>
        </bndbox>
    </object>    <object>
        <name>stop sign</name>
        <pose>Unspecified</pose>
        <truncated>0</truncated>
        <difficult>0.06364012</difficult>
        <bndbox>
            <xmin>345.13412</xmin>
            <ymin>98.064964</ymin>
            <xmax>364.1941</xmax>
            <ymax>124.47254</ymax>
        </bndbox>
    </object>    <object>
        <name>handbag</name>
        <pose>Unspecified</pose>
        <truncated>0</truncated>
        <difficult>0.063581824</difficult>
        <bndbox>
            <xmin>175.41153</xmin>
            <ymin>166.48836</ymin>
            <xmax>194.9714</xmax>
            <ymax>198.10857</ymax>
        </bndbox>
    </object>    <object>
        <name>chair</name>
        <pose>Unspecified</pose>
        <truncated>0</truncated>
        <difficult>0.063274086</difficult>
        <bndbox>
            <xmin>131.26936</xmin>
            <ymin>190.19257</ymin>
            <xmax>145.86482</xmax>
            <ymax>236.76773</ymax>
        </bndbox>
    </object>    <object>
        <name>person</name>
        <pose>Unspecified</pose>
        <truncated>0</truncated>
        <difficult>0.06294942</difficult>
        <bndbox>
            <xmin>243.44647</xmin>
            <ymin>156.34146</ymin>
            <xmax>258.52087</xmax>
            <ymax>195.82713</ymax>
        </bndbox>
    </object>    <object>
        <name>truck</name>
        <pose>Unspecified</pose>
        <truncated>0</truncated>
        <difficult>0.06251261</difficult>
        <bndbox>
            <xmin>134.94777</xmin>
            <ymin>189.6524</ymin>
            <xmax>263.8168</xmax>
            <ymax>265.39673</ymax>
        </bndbox>
    </object>    <object>
        <name>person</name>
        <pose>Unspecified</pose>
        <truncated>0</truncated>
        <difficult>0.06222731</difficult>
        <bndbox>
            <xmin>313.67368</xmin>
            <ymin>131.6739</ymin>
            <xmax>337.43542</xmax>
            <ymax>153.13916</ymax>
        </bndbox>
    </object>    <object>
        <name>backpack</name>
        <pose>Unspecified</pose>
        <truncated>0</truncated>
        <difficult>0.06080237</difficult>
        <bndbox>
            <xmin>297.63654</xmin>
            <ymin>148.85721</ymin>
            <xmax>330.75403</xmax>
            <ymax>174.7317</ymax>
        </bndbox>
    </object>    <object>
        <name>motorcycle</name>
        <pose>Unspecified</pose>
        <truncated>0</truncated>
        <difficult>0.06069702</difficult>
        <bndbox>
            <xmin>1.1801233</xmin>
            <ymin>134.27603</ymin>
            <xmax>49.709507</xmax>
            <ymax>214.25095</ymax>
        </bndbox>
    </object>    <object>
        <name>skateboard</name>
        <pose>Unspecified</pose>
        <truncated>0</truncated>
        <difficult>0.060572565</difficult>
        <bndbox>
            <xmin>271.46747</xmin>
            <ymin>166.56487</ymin>
            <xmax>285.71487</xmax>
            <ymax>178.00949</ymax>
        </bndbox>
    </object>    <object>
        <name>car</name>
        <pose>Unspecified</pose>
        <truncated>0</truncated>
        <difficult>0.06052807</difficult>
        <bndbox>
            <xmin>334.7843</xmin>
            <ymin>222.46896</ymin>
            <xmax>360.1151</xmax>
            <ymax>300.63248</ymax>
        </bndbox>
    </object>    <object>
        <name>suitcase</name>
        <pose>Unspecified</pose>
        <truncated>0</truncated>
        <difficult>0.060386717</difficult>
        <bndbox>
            <xmin>175.41153</xmin>
            <ymin>166.48836</ymin>
            <xmax>194.9714</xmax>
            <ymax>198.10857</ymax>
        </bndbox>
    </object>    <object>
        <name>truck</name>
        <pose>Unspecified</pose>
        <truncated>0</truncated>
        <difficult>0.059762657</difficult>
        <bndbox>
            <xmin>278.03854</xmin>
            <ymin>138.71439</ymin>
            <xmax>379.4301</xmax>
            <ymax>257.05148</ymax>
        </bndbox>
    </object>    <object>
        <name>person</name>
        <pose>Unspecified</pose>
        <truncated>0</truncated>
        <difficult>0.059681326</difficult>
        <bndbox>
            <xmin>299.22824</xmin>
            <ymin>167.37447</ymin>
            <xmax>364.0161</xmax>
            <ymax>202.31674</ymax>
        </bndbox>
    </object>    <object>
        <name>backpack</name>
        <pose>Unspecified</pose>
        <truncated>0</truncated>
        <difficult>0.059511572</difficult>
        <bndbox>
            <xmin>231.88942</xmin>
            <ymin>148.41943</ymin>
            <xmax>256.78232</xmax>
            <ymax>228.94798</ymax>
        </bndbox>
    </object>    <object>
        <name>bus</name>
        <pose>Unspecified</pose>
        <truncated>0</truncated>
        <difficult>0.05934933</difficult>
        <bndbox>
            <xmin>200.39384</xmin>
            <ymin>119.51727</ymin>
            <xmax>261.5246</xmax>
            <ymax>245.36517</ymax>
        </bndbox>
    </object>    <object>
        <name>motorcycle</name>
        <pose>Unspecified</pose>
        <truncated>0</truncated>
        <difficult>0.059129924</difficult>
        <bndbox>
            <xmin>301.5712</xmin>
            <ymin>160.85977</ymin>
            <xmax>355.99463</xmax>
            <ymax>256.23758</ymax>
        </bndbox>
    </object>    <object>
        <name>motorcycle</name>
        <pose>Unspecified</pose>
        <truncated>0</truncated>
        <difficult>0.059096128</difficult>
        <bndbox>
            <xmin>275.0653</xmin>
            <ymin>165.78554</ymin>
            <xmax>317.418</xmax>
            <ymax>227.4277</ymax>
        </bndbox>
    </object>    <object>
        <name>motorcycle</name>
        <pose>Unspecified</pose>
        <truncated>0</truncated>
        <difficult>0.05861485</difficult>
        <bndbox>
            <xmin>334.15265</xmin>
            <ymin>225.76181</ymin>
            <xmax>360.33365</xmax>
            <ymax>301.40097</ymax>
        </bndbox>
    </object>    <object>
        <name>motorcycle</name>
        <pose>Unspecified</pose>
        <truncated>0</truncated>
        <difficult>0.05845484</difficult>
        <bndbox>
            <xmin>275.58438</xmin>
            <ymin>195.67969</ymin>
            <xmax>330.9125</xmax>
            <ymax>296.03418</ymax>
        </bndbox>
    </object>    <object>
        <name>motorcycle</name>
        <pose>Unspecified</pose>
        <truncated>0</truncated>
        <difficult>0.058400124</difficult>
        <bndbox>
            <xmin>230.62956</xmin>
            <ymin>143.62155</ymin>
            <xmax>263.14694</xmax>
            <ymax>254.61665</ymax>
        </bndbox>
    </object>    <object>
        <name>motorcycle</name>
        <pose>Unspecified</pose>
        <truncated>0</truncated>
        <difficult>0.057912588</difficult>
        <bndbox>
            <xmin>163.21873</xmin>
            <ymin>206.27457</ymin>
            <xmax>194.81989</xmax>
            <ymax>264.2522</ymax>
        </bndbox>
    </object>    <object>
        <name>motorcycle</name>
        <pose>Unspecified</pose>
        <truncated>0</truncated>
        <difficult>0.057790726</difficult>
        <bndbox>
            <xmin>329.5492</xmin>
            <ymin>182.98715</ymin>
            <xmax>372.74405</xmax>
            <ymax>304.7166</ymax>
        </bndbox>
    </object>    <object>
        <name>backpack</name>
        <pose>Unspecified</pose>
        <truncated>0</truncated>
        <difficult>0.057370663</difficult>
        <bndbox>
            <xmin>285.4095</xmin>
            <ymin>171.71779</ymin>
            <xmax>356.61603</xmax>
            <ymax>203.21678</ymax>
        </bndbox>
    </object>    <object>
        <name>person</name>
        <pose>Unspecified</pose>
        <truncated>0</truncated>
        <difficult>0.05736634</difficult>
        <bndbox>
            <xmin>34.821198</xmin>
            <ymin>112.82802</ymin>
            <xmax>117.32955</xmax>
            <ymax>210.63474</ymax>
        </bndbox>
    </object>    <object>
        <name>suitcase</name>
        <pose>Unspecified</pose>
        <truncated>0</truncated>
        <difficult>0.057240754</difficult>
        <bndbox>
            <xmin>338.02606</xmin>
            <ymin>214.09799</ymin>
            <xmax>360.25296</xmax>
            <ymax>285.57214</ymax>
        </bndbox>
    </object>    <object>
        <name>person</name>
        <pose>Unspecified</pose>
        <truncated>0</truncated>
        <difficult>0.057106614</difficult>
        <bndbox>
            <xmin>306.30133</xmin>
            <ymin>131.03078</ymin>
            <xmax>339.40784</xmax>
            <ymax>163.88356</ymax>
        </bndbox>
    </object>    <object>
        <name>car</name>
        <pose>Unspecified</pose>
        <truncated>0</truncated>
        <difficult>0.057010055</difficult>
        <bndbox>
            <xmin>376.4479</xmin>
            <ymin>159.82239</ymin>
            <xmax>414.46802</xmax>
            <ymax>179.80075</ymax>
        </bndbox>
    </object>    <object>
        <name>truck</name>
        <pose>Unspecified</pose>
        <truncated>0</truncated>
        <difficult>0.056771666</difficult>
        <bndbox>
            <xmin>51.003098</xmin>
            <ymin>104.26499</ymin>
            <xmax>285.89328</xmax>
            <ymax>267.75793</ymax>
        </bndbox>
    </object>    <object>
        <name>person</name>
        <pose>Unspecified</pose>
        <truncated>0</truncated>
        <difficult>0.056533992</difficult>
        <bndbox>
            <xmin>313.74155</xmin>
            <ymin>145.73682</ymin>
            <xmax>346.60446</xmax>
            <ymax>177.54611</ymax>
        </bndbox>
    </object>    <object>
        <name>backpack</name>
        <pose>Unspecified</pose>
        <truncated>0</truncated>
        <difficult>0.056368023</difficult>
        <bndbox>
            <xmin>227.65378</xmin>
            <ymin>180.97614</ymin>
            <xmax>253.30154</xmax>
            <ymax>250.53549</ymax>
        </bndbox>
    </object>    <object>
        <name>person</name>
        <pose>Unspecified</pose>
        <truncated>0</truncated>
        <difficult>0.056001604</difficult>
        <bndbox>
            <xmin>243.91132</xmin>
            <ymin>148.99814</ymin>
            <xmax>255.55725</xmax>
            <ymax>170.5655</ymax>
        </bndbox>
    </object>    <object>
        <name>person</name>
        <pose>Unspecified</pose>
        <truncated>0</truncated>
        <difficult>0.055825084</difficult>
        <bndbox>
            <xmin>153.60214</xmin>
            <ymin>138.05803</ymin>
            <xmax>170.00253</xmax>
            <ymax>168.5472</ymax>
        </bndbox>
    </object>    <object>
        <name>person</name>
        <pose>Unspecified</pose>
        <truncated>0</truncated>
        <difficult>0.05572185</difficult>
        <bndbox>
            <xmin>232.95683</xmin>
            <ymin>148.5195</ymin>
            <xmax>249.18272</xmax>
            <ymax>186.67752</ymax>
        </bndbox>
    </object>    <object>
        <name>car</name>
        <pose>Unspecified</pose>
        <truncated>0</truncated>
        <difficult>0.055704236</difficult>
        <bndbox>
            <xmin>271.32404</xmin>
            <ymin>166.43834</ymin>
            <xmax>286.21188</xmax>
            <ymax>177.81702</ymax>
        </bndbox>
    </object>    <object>
        <name>handbag</name>
        <pose>Unspecified</pose>
        <truncated>0</truncated>
        <difficult>0.055698037</difficult>
        <bndbox>
            <xmin>57.15052</xmin>
            <ymin>207.74109</ymin>
            <xmax>66.689445</xmax>
            <ymax>222.92577</ymax>
        </bndbox>
    </object>    <object>
        <name>person</name>
        <pose>Unspecified</pose>
        <truncated>0</truncated>
        <difficult>0.055682093</difficult>
        <bndbox>
            <xmin>232.98175</xmin>
            <ymin>125.13736</ymin>
            <xmax>375.2212</xmax>
            <ymax>277.25098</ymax>
        </bndbox>
    </object>    <object>
        <name>truck</name>
        <pose>Unspecified</pose>
        <truncated>0</truncated>
        <difficult>0.05560544</difficult>
        <bndbox>
            <xmin>243.02266</xmin>
            <ymin>123.23549</ymin>
            <xmax>405.82608</xmax>
            <ymax>212.84364</ymax>
        </bndbox>
    </object>    <object>
        <name>kite</name>
        <pose>Unspecified</pose>
        <truncated>0</truncated>
        <difficult>0.055528373</difficult>
        <bndbox>
            <xmin>377.30646</xmin>
            <ymin>102.89983</ymin>
            <xmax>395.27206</xmax>
            <ymax>127.1574</ymax>
        </bndbox>
    </object>    <object>
        <name>person</name>
        <pose>Unspecified</pose>
        <truncated>0</truncated>
        <difficult>0.05530864</difficult>
        <bndbox>
            <xmin>450.86502</xmin>
            <ymin>162.18443</ymin>
            <xmax>465.11548</xmax>
            <ymax>172.96234</ymax>
        </bndbox>
    </object>    <object>
        <name>backpack</name>
        <pose>Unspecified</pose>
        <truncated>0</truncated>
        <difficult>0.05506885</difficult>
        <bndbox>
            <xmin>131.28784</xmin>
            <ymin>192.49348</ymin>
            <xmax>144.06447</xmax>
            <ymax>236.23096</ymax>
        </bndbox>
    </object>    <object>
        <name>cell phone</name>
        <pose>Unspecified</pose>
        <truncated>0</truncated>
        <difficult>0.054853827</difficult>
        <bndbox>
            <xmin>175.18327</xmin>
            <ymin>166.67322</ymin>
            <xmax>195.49379</xmax>
            <ymax>196.76178</ymax>
        </bndbox>
    </object>    <object>
        <name>handbag</name>
        <pose>Unspecified</pose>
        <truncated>0</truncated>
        <difficult>0.05482462</difficult>
        <bndbox>
            <xmin>172.94667</xmin>
            <ymin>166.42531</ymin>
            <xmax>195.6485</xmax>
            <ymax>222.80727</ymax>
        </bndbox>
    </object>    <object>
        <name>person</name>
        <pose>Unspecified</pose>
        <truncated>0</truncated>
        <difficult>0.054790348</difficult>
        <bndbox>
            <xmin>325.51364</xmin>
            <ymin>159.77313</ymin>
            <xmax>349.85123</xmax>
            <ymax>195.05731</ymax>
        </bndbox>
    </object>    <object>
        <name>parking meter</name>
        <pose>Unspecified</pose>
        <truncated>0</truncated>
        <difficult>0.054576933</difficult>
        <bndbox>
            <xmin>144.4659</xmin>
            <ymin>117.883575</ymin>
            <xmax>278.25366</xmax>
            <ymax>265.78946</ymax>
        </bndbox>
    </object>    <object>
        <name>backpack</name>
        <pose>Unspecified</pose>
        <truncated>0</truncated>
        <difficult>0.054509044</difficult>
        <bndbox>
            <xmin>285.98325</xmin>
            <ymin>168.25835</ymin>
            <xmax>352.26035</xmax>
            <ymax>253.09694</ymax>
        </bndbox>
    </object>    <object>
        <name>backpack</name>
        <pose>Unspecified</pose>
        <truncated>0</truncated>
        <difficult>0.054501593</difficult>
        <bndbox>
            <xmin>164.01767</xmin>
            <ymin>196.72153</ymin>
            <xmax>195.2958</xmax>
            <ymax>260.41705</ymax>
        </bndbox>
    </object>    <object>
        <name>bottle</name>
        <pose>Unspecified</pose>
        <truncated>0</truncated>
        <difficult>0.054065466</difficult>
        <bndbox>
            <xmin>57.412395</xmin>
            <ymin>207.60149</ymin>
            <xmax>66.54308</xmax>
            <ymax>222.68939</ymax>
        </bndbox>
    </object>    <object>
        <name>motorcycle</name>
        <pose>Unspecified</pose>
        <truncated>0</truncated>
        <difficult>0.053992003</difficult>
        <bndbox>
            <xmin>264.4052</xmin>
            <ymin>165.17531</ymin>
            <xmax>310.5001</xmax>
            <ymax>261.19754</ymax>
        </bndbox>
    </object>    <object>
        <name>person</name>
        <pose>Unspecified</pose>
        <truncated>0</truncated>
        <difficult>0.053871453</difficult>
        <bndbox>
            <xmin>135.58403</xmin>
            <ymin>170.63248</ymin>
            <xmax>259.4847</xmax>
            <ymax>263.38034</ymax>
        </bndbox>
    </object>    <object>
        <name>dog</name>
        <pose>Unspecified</pose>
        <truncated>0</truncated>
        <difficult>0.05383706</difficult>
        <bndbox>
            <xmin>171.22902</xmin>
            <ymin>164.80959</ymin>
            <xmax>195.66675</xmax>
            <ymax>225.32706</ymax>
        </bndbox>
    </object>    <object>
        <name>car</name>
        <pose>Unspecified</pose>
        <truncated>0</truncated>
        <difficult>0.053691894</difficult>
        <bndbox>
            <xmin>204.49084</xmin>
            <ymin>127.45964</ymin>
            <xmax>262.40906</xmax>
            <ymax>256.0472</ymax>
        </bndbox>
    </object>    <object>
        <name>backpack</name>
        <pose>Unspecified</pose>
        <truncated>0</truncated>
        <difficult>0.05357808</difficult>
        <bndbox>
            <xmin>17.186995</xmin>
            <ymin>115.527794</ymin>
            <xmax>67.77621</xmax>
            <ymax>216.21114</ymax>
        </bndbox>
    </object>    <object>
        <name>person</name>
        <pose>Unspecified</pose>
        <truncated>0</truncated>
        <difficult>0.053561836</difficult>
        <bndbox>
            <xmin>268.48672</xmin>
            <ymin>163.08975</ymin>
            <xmax>348.97342</xmax>
            <ymax>203.48566</ymax>
        </bndbox>
    </object>    <object>
        <name>car</name>
        <pose>Unspecified</pose>
        <truncated>0</truncated>
        <difficult>0.053343624</difficult>
        <bndbox>
            <xmin>377.10162</xmin>
            <ymin>161.44067</ymin>
            <xmax>402.22662</xmax>
            <ymax>191.06126</ymax>
        </bndbox>
    </object>    <object>
        <name>suitcase</name>
        <pose>Unspecified</pose>
        <truncated>0</truncated>
        <difficult>0.053330302</difficult>
        <bndbox>
            <xmin>174.78276</xmin>
            <ymin>177.88823</ymin>
            <xmax>193.78029</xmax>
            <ymax>205.93811</ymax>
        </bndbox>
    </object>    <object>
        <name>frisbee</name>
        <pose>Unspecified</pose>
        <truncated>0</truncated>
        <difficult>0.053305358</difficult>
        <bndbox>
            <xmin>180.25389</xmin>
            <ymin>166.72574</ymin>
            <xmax>191.17738</xmax>
            <ymax>176.17073</ymax>
        </bndbox>
    </object>    <object>
        <name>motorcycle</name>
        <pose>Unspecified</pose>
        <truncated>0</truncated>
        <difficult>0.0530982</difficult>
        <bndbox>
            <xmin>37.055084</xmin>
            <ymin>137.54817</ymin>
            <xmax>71.094986</xmax>
            <ymax>227.77307</ymax>
        </bndbox>
    </object>    <object>
        <name>motorcycle</name>
        <pose>Unspecified</pose>
        <truncated>0</truncated>
        <difficult>0.05305311</difficult>
        <bndbox>
            <xmin>293.98508</xmin>
            <ymin>187.77357</ymin>
            <xmax>359.06232</xmax>
            <ymax>284.78238</ymax>
        </bndbox>
    </object>    <object>
        <name>person</name>
        <pose>Unspecified</pose>
        <truncated>0</truncated>
        <difficult>0.052940756</difficult>
        <bndbox>
            <xmin>23.735142</xmin>
            <ymin>107.94854</ymin>
            <xmax>48.12944</xmax>
            <ymax>138.64226</ymax>
        </bndbox>
    </object>    <object>
        <name>person</name>
        <pose>Unspecified</pose>
        <truncated>0</truncated>
        <difficult>0.052820444</difficult>
        <bndbox>
            <xmin>330.85846</xmin>
            <ymin>171.15842</ymin>
            <xmax>356.7076</xmax>
            <ymax>204.38329</ymax>
        </bndbox>
    </object>    <object>
        <name>motorcycle</name>
        <pose>Unspecified</pose>
        <truncated>0</truncated>
        <difficult>0.052554697</difficult>
        <bndbox>
            <xmin>272.76892</xmin>
            <ymin>192.62488</ymin>
            <xmax>289.41754</xmax>
            <ymax>201.38416</ymax>
        </bndbox>
    </object>    <object>
        <name>person</name>
        <pose>Unspecified</pose>
        <truncated>0</truncated>
        <difficult>0.05255258</difficult>
        <bndbox>
            <xmin>236.99498</xmin>
            <ymin>146.43835</ymin>
            <xmax>253.91075</xmax>
            <ymax>167.2582</ymax>
        </bndbox>
    </object>    <object>
        <name>person</name>
        <pose>Unspecified</pose>
        <truncated>0</truncated>
        <difficult>0.052371264</difficult>
        <bndbox>
            <xmin>132.79355</xmin>
            <ymin>190.2584</ymin>
            <xmax>142.65945</xmax>
            <ymax>220.07114</ymax>
        </bndbox>
    </object>    <object>
        <name>backpack</name>
        <pose>Unspecified</pose>
        <truncated>0</truncated>
        <difficult>0.052277416</difficult>
        <bndbox>
            <xmin>330.9956</xmin>
            <ymin>159.28989</ymin>
            <xmax>339.47675</xmax>
            <ymax>182.64046</ymax>
        </bndbox>
    </object>    <object>
        <name>person</name>
        <pose>Unspecified</pose>
        <truncated>0</truncated>
        <difficult>0.051927716</difficult>
        <bndbox>
            <xmin>130.30257</xmin>
            <ymin>161.28017</ymin>
            <xmax>150.66896</xmax>
            <ymax>237.05734</ymax>
        </bndbox>
    </object>    <object>
        <name>bicycle</name>
        <pose>Unspecified</pose>
        <truncated>0</truncated>
        <difficult>0.051756382</difficult>
        <bndbox>
            <xmin>283.0612</xmin>
            <ymin>234.6443</ymin>
            <xmax>312.78326</xmax>
            <ymax>294.874</ymax>
        </bndbox>
    </object>    <object>
        <name>backpack</name>
        <pose>Unspecified</pose>
        <truncated>0</truncated>
        <difficult>0.05170408</difficult>
        <bndbox>
            <xmin>330.8031</xmin>
            <ymin>209.78098</ymin>
            <xmax>345.8627</xmax>
            <ymax>241.41138</ymax>
        </bndbox>
    </object>    <object>
        <name>person</name>
        <pose>Unspecified</pose>
        <truncated>0</truncated>
        <difficult>0.05162725</difficult>
        <bndbox>
            <xmin>318.20062</xmin>
            <ymin>130.20546</ymin>
            <xmax>395.75708</xmax>
            <ymax>218.09612</ymax>
        </bndbox>
    </object>    <object>
        <name>truck</name>
        <pose>Unspecified</pose>
        <truncated>0</truncated>
        <difficult>0.051413834</difficult>
        <bndbox>
            <xmin>399.12213</xmin>
            <ymin>157.46332</ymin>
            <xmax>466.40335</xmax>
            <ymax>208.85007</ymax>
        </bndbox>
    </object>    <object>
        <name>person</name>
        <pose>Unspecified</pose>
        <truncated>0</truncated>
        <difficult>0.051322937</difficult>
        <bndbox>
            <xmin>277.7285</xmin>
            <ymin>185.34482</ymin>
            <xmax>348.67017</xmax>
            <ymax>225.20781</ymax>
        </bndbox>
    </object>    <object>
        <name>traffic light</name>
        <pose>Unspecified</pose>
        <truncated>0</truncated>
        <difficult>0.051209778</difficult>
        <bndbox>
            <xmin>390.6711</xmin>
            <ymin>106.542984</ymin>
            <xmax>398.17123</xmax>
            <ymax>127.58497</ymax>
        </bndbox>
    </object>    <object>
        <name>person</name>
        <pose>Unspecified</pose>
        <truncated>0</truncated>
        <difficult>0.05117041</difficult>
        <bndbox>
            <xmin>151.2478</xmin>
            <ymin>146.61145</ymin>
            <xmax>161.52612</xmax>
            <ymax>163.84035</ymax>
        </bndbox>
    </object>    <object>
        <name>motorcycle</name>
        <pose>Unspecified</pose>
        <truncated>0</truncated>
        <difficult>0.051068127</difficult>
        <bndbox>
            <xmin>275.37598</xmin>
            <ymin>182.35089</ymin>
            <xmax>295.3678</xmax>
            <ymax>201.91362</ymax>
        </bndbox>
    </object>    <object>
        <name>mouse</name>
        <pose>Unspecified</pose>
        <truncated>0</truncated>
        <difficult>0.051024318</difficult>
        <bndbox>
            <xmin>271.3297</xmin>
            <ymin>166.4698</ymin>
            <xmax>286.04272</xmax>
            <ymax>177.9371</ymax>
        </bndbox>
    </object>    <object>
        <name>car</name>
        <pose>Unspecified</pose>
        <truncated>0</truncated>
        <difficult>0.050934136</difficult>
        <bndbox>
            <xmin>10.18162</xmin>
            <ymin>205.74968</ymin>
            <xmax>64.649155</xmax>
            <ymax>250.71228</ymax>
        </bndbox>
    </object>    <object>
        <name>person</name>
        <pose>Unspecified</pose>
        <truncated>0</truncated>
        <difficult>0.050769</difficult>
        <bndbox>
            <xmin>173.43205</xmin>
            <ymin>183.9992</ymin>
            <xmax>191.17058</xmax>
            <ymax>221.73044</ymax>
        </bndbox>
    </object>    <object>
        <name>backpack</name>
        <pose>Unspecified</pose>
        <truncated>0</truncated>
        <difficult>0.050319076</difficult>
        <bndbox>
            <xmin>13.44743</xmin>
            <ymin>144.23778</ymin>
            <xmax>64.98402</xmax>
            <ymax>173.35272</ymax>
        </bndbox>
    </object>    <object>
        <name>car</name>
        <pose>Unspecified</pose>
        <truncated>0</truncated>
        <difficult>0.05026704</difficult>
        <bndbox>
            <xmin>428.75668</xmin>
            <ymin>154.5256</ymin>
            <xmax>477.76328</xmax>
            <ymax>183.05368</ymax>
        </bndbox>
    </object>    <object>
        <name>backpack</name>
        <pose>Unspecified</pose>
        <truncated>0</truncated>
        <difficult>0.050236434</difficult>
        <bndbox>
            <xmin>49.396507</xmin>
            <ymin>116.133354</ymin>
            <xmax>69.12477</xmax>
            <ymax>167.9672</ymax>
        </bndbox>
    </object>    <object>
        <name>person</name>
        <pose>Unspecified</pose>
        <truncated>0</truncated>
        <difficult>0.050120592</difficult>
        <bndbox>
            <xmin>377.5558</xmin>
            <ymin>160.61307</ymin>
            <xmax>420.5532</xmax>
            <ymax>195.4428</ymax>
        </bndbox>
    </object>    <object>
        <name>backpack</name>
        <pose>Unspecified</pose>
        <truncated>0</truncated>
        <difficult>0.05007866</difficult>
        <bndbox>
            <xmin>312.0084</xmin>
            <ymin>157.99979</ymin>
            <xmax>328.62372</xmax>
            <ymax>176.05737</ymax>
        </bndbox>
    </object>    <object>
        <name>person</name>
        <pose>Unspecified</pose>
        <truncated>0</truncated>
        <difficult>0.05003947</difficult>
        <bndbox>
            <xmin>467.7852</xmin>
            <ymin>179.1473</ymin>
            <xmax>481.16248</xmax>
            <ymax>217.83086</ymax>
        </bndbox>
    </object>    <object>
        <name>backpack</name>
        <pose>Unspecified</pose>
        <truncated>0</truncated>
        <difficult>0.050017416</difficult>
        <bndbox>
            <xmin>271.61472</xmin>
            <ymin>166.37941</ymin>
            <xmax>286.21658</xmax>
            <ymax>177.96548</ymax>
        </bndbox>
    </object>
</annotation>
